fbbotw/__init__.py
fbbotw/fbbotw.py
fbbotw-2.2.1.dist-info/METADATA
fbbotw-2.2.1.dist-info/RECORD
fbbotw-2.2.1.dist-info/WHEEL
fbbotw-2.2.1.dist-info/top_level.txt
