Metadata-Version: 2.1
Name: fbbotw
Version: 2.2.1
Summary: Python/Django Wrapper for Facebook Messenger Bot Platform.
Home-page: https://github.com/JoabMendes/fbbotw
Author: Joabe Mendes
Author-email: joabe.mdl@gmail.com
License: MIT
Keywords: facebook bot mensseger platform wrapper django
Platform: UNKNOWN
Classifier: Development Status :: 5 - Production/Stable
Classifier: Intended Audience :: Developers
Classifier: Topic :: Software Development :: Build Tools
Classifier: License :: OSI Approved :: MIT License
Classifier: Programming Language :: Python :: 3.5
Classifier: Environment :: Web Environment
Classifier: Framework :: Django
Classifier: Natural Language :: English
Classifier: Topic :: Software Development :: Libraries
Requires-Dist: requests
